amp_renderer/__init__.py
tests/__init__.py
tests/test_against_spec.py
tests/test_amp_node.py
tests/test_amp_renderer.py
tests/test_speed.py
amp_renderer-2.0.1.dist-info/LICENSE
amp_renderer-2.0.1.dist-info/METADATA
amp_renderer-2.0.1.dist-info/WHEEL
amp_renderer-2.0.1.dist-info/top_level.txt
amp_renderer-2.0.1.dist-info/RECORD
