Metadata-Version: 2.1
Name: amp-renderer
Version: 2.0.1
Summary: Unofficial Python port of server-side rendering from AMP Optimizer
Home-page: https://github.com/chasefinch/amp-renderer
Author: Chase Finch
Author-email: chase@finch.email
License: UNKNOWN
Keywords: AMP,AMP Optimizer,server-side rendering
Platform: UNKNOWN
Classifier: Programming Language :: Python :: 3
Classifier: Programming Language :: Python :: 3.6
Classifier: Programming Language :: Python :: 3.7
Classifier: Programming Language :: Python :: 3.8
Classifier: Programming Language :: Python :: 3.9
Classifier: License :: OSI Approved :: Apache Software License
Classifier: Operating System :: OS Independent
Requires-Python: >=3.6
License-File: LICENSE
